DjPj-0.6.0.dist-info/DESCRIPTION.rst
DjPj-0.6.0.dist-info/METADATA
DjPj-0.6.0.dist-info/RECORD
DjPj-0.6.0.dist-info/WHEEL
DjPj-0.6.0.dist-info/metadata.json
DjPj-0.6.0.dist-info/top_level.txt
djpj/__init__.py
djpj/compat.py
djpj/decorator.py
djpj/middleware.py
djpj/template.py
djpj/utils.py
